wingmonkey/__init__.py
wingmonkey/async_operations.py
wingmonkey/batch_operations.py
wingmonkey/enums.py
wingmonkey/factories.py
wingmonkey/lists.py
wingmonkey/mailchimp_account.py
wingmonkey/mailchimp_base.py
wingmonkey/mailchimp_export.py
wingmonkey/mailchimp_session.py
wingmonkey/members.py
wingmonkey/merge_fields.py
wingmonkey/segments.py
wingmonkey/settings.py
wingmonkey/scripts/__init__.py
wingmonkey/scripts/import_all_members.py
wingmonkey/scripts/import_members_csv.py
wingmonkey/scripts/update_members.py
wingmonkey/tests/__init__.py
wingmonkey/tests/test_async_operations.py
wingmonkey/tests/test_batch_operations.py
wingmonkey/tests/test_lists.py
wingmonkey/tests/test_mailchimp_account.py
wingmonkey/tests/test_mailchimp_export.py
wingmonkey/tests/test_mailchimp_session.py
wingmonkey/tests/test_members.py
wingmonkey/tests/test_merge_fields.py
wingmonkey/tests/test_segments.py
wingmonkey-0.1.21.dist-info/METADATA
wingmonkey-0.1.21.dist-info/WHEEL
wingmonkey-0.1.21.dist-info/top_level.txt
wingmonkey-0.1.21.dist-info/RECORD
