Metadata-Version: 2.1
Name: wingmonkey
Version: 0.1.21
Summary: mailchimp api v3 client
Home-page: https://github.com/vikingco/wingmonkey
Author: Jonas Steur
Author-email: jonas.steur@unleashed.be
License: BSD
Platform: UNKNOWN
Classifier: Intended Audience :: Developers
Classifier: Programming Language :: Python
Classifier: Programming Language :: Python :: 3 :: Only
Classifier: Programming Language :: Python :: 3.6
Classifier: Operating System :: OS Independent
Classifier: Environment :: Web Environment
Requires-Dist: requests (==2.20.0)
Requires-Dist: aiohttp (==2.2.5)
Requires-Dist: async-timeout (==1.2.1)
Requires-Dist: chardet (==3.0.4)
Requires-Dist: multidict (==3.1.3)
Requires-Dist: yarl (==0.12.0)
Requires-Dist: django-environ (==0.4.3)
Requires-Dist: marshmallow (==v3.0.0b2)
